plans/0-overview-template.md
plans/N-phase-template.md
plans/PLAN_AUDIT_SUMMARY.md
plans/TEMPLATE-USAGE-GUIDE.md
plans/__init__.py
plans/abandoned-plans-archive-2025.tar.gz
plans/agents-architecture-archive-2025.tar.gz
plans/closeout-template.md
plans/completed-plans-archive-2025.tar.gz
plans/completed-plans-documentation-archive-2025.tar.gz
plans/completed-plans-minimal-archive-2025.tar.gz
plans/custom-gpt-archive-2025.tar.gz
plans/duplicate-object-warnings-fix-plan.md
plans/issues_from_plans.py
plans/root-stale-docs-archive-2025.tar.gz
plans/sphinx-warnings-analysis.md
plans/.velocity/metrics.json
plans/documentation-rebuild-session/compacted_state.md
plans/github-issues-migration/0-Overview.md
plans/github-issues-migration/1-Foundation-Label-System.md
plans/github-issues-migration/2-Migration-Tool-Rewrite.md
plans/github-issues-migration/2-Plan-Creation-System.md
plans/github-issues-migration/3-CLI-Integration-Automation.md
plans/github-issues-migration/3-CLI-Integration-Documentation.md
plans/github-issues-migration/4-Plan-Closeout-Validation.md
plans/github-issues-migration/4-Validated-Migration.md
plans/github-issues-migration/5-Documentation-Training.md
plans/github-issues-migration/6-Closeout.md
plans/github-workflows-repair/repair-plan.md
plans/session-compaction-2025-08-12/compacted_state.md
plans/session-compaction-2025-08-13/compacted_state.md
plans/session-continuity-protocol/0-Overview.md
plans/session-continuity-protocol/1-Core-Principles-Framework.md
plans/session-continuity-protocol/2-Pre-Session-Validation-System.md
plans/session-continuity-protocol/3-Context-Switching-Prevention.md
plans/session-continuity-protocol/4-Progress-Tracking-Recovery.md
plans/tests-audit/0-Overview.md
plans/tests-audit/1-Discovery-Inventory.md
plans/tests-audit/2-Physics-Validation-Audit.md
plans/tests-audit/3-Architecture-Compliance.md
plans/tests-audit/4-Numerical-Stability-Analysis.md
plans/tests-audit/5-Documentation-Enhancement.md
solarwindpy-0.2.0.dist-info/licenses/LICENSE
solarwindpy-0.2.0.dist-info/METADATA
solarwindpy-0.2.0.dist-info/WHEEL
solarwindpy-0.2.0.dist-info/top_level.txt
solarwindpy-0.2.0.dist-info/RECORD
