Metadata-Version: 2.4
Name: solarwindpy
Version: 0.2.0
Summary: Python package for solar wind data analysis.
Author-email: "B. L. Alterman" <blaltermanphd@gmail.com>
License: BSD 3-Clause License
Project-URL: Bug Tracker, https://github.com/blalterman/SolarWindPy/issues
Project-URL: Source, https://github.com/blalterman/SolarWindPy
Keywords: plasma,physics,solar wind,measurements,in situ,spacecraft
Classifier: Development Status :: 3 - Alpha
Classifier: Intended Audience :: Developers
Classifier: License :: OSI Approved :: BSD License
Classifier: Programming Language :: Python :: 3
Classifier: Programming Language :: Python :: 3.11
Classifier: Programming Language :: Python :: 3.12
Classifier: Programming Language :: Python :: 3.13
Classifier: Intended Audience :: Science/Research
Classifier: Intended Audience :: Education
Classifier: Topic :: Scientific/Engineering
Classifier: Topic :: Scientific/Engineering :: Physics
Requires-Python: <4,>=3.11
License-File: LICENSE
Requires-Dist: numpy<2.0,>=1.22
Requires-Dist: scipy>=1.10
Requires-Dist: pandas>=1.5
Requires-Dist: numexpr>=2.8
Requires-Dist: bottleneck>=1.3
Requires-Dist: h5py>=3.8
Requires-Dist: pyyaml>=6.0
Requires-Dist: matplotlib>=3.5
Requires-Dist: astropy>=5.0
Requires-Dist: numba>=0.57
Requires-Dist: tabulate>=0.9
Requires-Dist: docstring-inheritance>=2.0
Provides-Extra: dev
Requires-Dist: pytest>=7.4.4; extra == "dev"
Requires-Dist: pytest-cov>=4.1.0; extra == "dev"
Requires-Dist: black; extra == "dev"
Requires-Dist: flake8; extra == "dev"
Requires-Dist: doc8; extra == "dev"
Requires-Dist: flake8-docstrings; extra == "dev"
Requires-Dist: pydocstyle; extra == "dev"
Requires-Dist: numpydoc; extra == "dev"
Requires-Dist: sphinx; extra == "dev"
Requires-Dist: sphinx_rtd_theme; extra == "dev"
Requires-Dist: sphinxcontrib-spelling; extra == "dev"
Requires-Dist: sphinxcontrib-bibtex; extra == "dev"
Requires-Dist: docstring-inheritance>=2.0; extra == "dev"
Provides-Extra: test
Requires-Dist: pytest>=7.4.4; extra == "test"
Requires-Dist: pytest-cov>=4.1.0; extra == "test"
Dynamic: license-file
